relumip/__init__.py
relumip/ann_model.py
relumip/interfaces/__init__.py
relumip/interfaces/gurobi_modeling_interface.py
relumip/interfaces/interface_factory.py
relumip/interfaces/modeling_interface.py
relumip/interfaces/pyomo_modeling_interface.py
relumip/interfaces/supported_modeling_languages.py
relumip/utils/__init__.py
relumip/utils/storage.py
relumip/utils/visualization.py
reluMIP-1.0.0.dist-info/LICENSE
reluMIP-1.0.0.dist-info/METADATA
reluMIP-1.0.0.dist-info/WHEEL
reluMIP-1.0.0.dist-info/top_level.txt
reluMIP-1.0.0.dist-info/RECORD
