Metadata-Version: 2.1
Name: reluMIP
Version: 1.0.0
Summary: Embed tensorflow ReLU neural networks in MIP optimization problems.
Home-page: https://github.com/ChemEngAI/ReLU_ANN_MILP
Author: Laurens Lueg, Artur Schweidtmann
Author-email: A.Schweidtmann@tudelft.nl.de
License: MIT
Platform: UNKNOWN
Classifier: License :: OSI Approved :: MIT License
Classifier: Programming Language :: Python :: 3
Classifier: Programming Language :: Python :: 3.7
License-File: LICENSE
Requires-Dist: numpy
Requires-Dist: tensorflow
Requires-Dist: tqdm
Requires-Dist: matplotlib
Requires-Dist: pyomo
Requires-Dist: gurobipy
